jax_f16/__init__.py
jax_f16/f16.py
jax_f16/f16_types.py
jax_f16/f16_utils.py
jax_f16/controllers/__init__.py
jax_f16/controllers/pid.py
jax_f16/highlevel/__init__.py
jax_f16/highlevel/controlled_f16.py
jax_f16/lowlevel/__init__.py
jax_f16/lowlevel/adc.py
jax_f16/lowlevel/dampp.py
jax_f16/lowlevel/low_level_controller.py
jax_f16/lowlevel/morellif16.py
jax_f16/lowlevel/pdot.py
jax_f16/lowlevel/rtau.py
jax_f16/lowlevel/subf16_model.py
jax_f16/lowlevel/tgear.py
jax_f16/lowlevel/thrust.py
jax_f16/utils/__init__.py
jax_f16/utils/jax_types.py
jax_f16-0.0.2.dist-info/LICENSE.txt
jax_f16-0.0.2.dist-info/METADATA
jax_f16-0.0.2.dist-info/WHEEL
jax_f16-0.0.2.dist-info/top_level.txt
jax_f16-0.0.2.dist-info/RECORD
