Metadata-Version: 2.1
Name: jax-f16
Version: 0.0.2
Summary: Jax F16 dynamics
Author: Oswin So
Author-email: oswinso@gmail.com
Maintainer: Oswin So
Maintainer-email: oswinso@gmail.com
License: GNU GENERAL PUBLIC LICENSE
Project-URL: Homepage, https://mit-realm.github.io/efppo
Project-URL: documentation, https://github.com/mit-realm/jax-f16
Project-URL: repository, https://github.com/mit-realm/jax-f16
Project-URL: changelog, https://github.com/mit-realm/jax-f16/blob/main/CHANGELOG.md
Classifier: License :: OSI Approved :: GNU General Public License v3 (GPLv3)
Classifier: Programming Language :: Python
Requires-Python: >=3.10
License-File: LICENSE.txt
Requires-Dist: jax
Requires-Dist: jaxtyping
Provides-Extra: dev
Requires-Dist: pytest ==5.0.0 ; extra == 'dev'
Requires-Dist: pytest-cov[all] ; extra == 'dev'
Requires-Dist: mypy ==0.910 ; extra == 'dev'
Requires-Dist: black ==21.10b0 ; extra == 'dev'
